RobotFrameworkSlackNotifier1/RobotFrameworkSlackNotifier1.py
RobotFrameworkSlackNotifier1/__init__.py
RobotFrameworkSlackNotifier1/__main__.py
RobotFrameworkSlackNotifier1-0.0.1.dist-info/METADATA
RobotFrameworkSlackNotifier1-0.0.1.dist-info/WHEEL
RobotFrameworkSlackNotifier1-0.0.1.dist-info/top_level.txt
RobotFrameworkSlackNotifier1-0.0.1.dist-info/RECORD
