Metadata-Version: 2.1
Name: RobotFrameworkSlackNotifier1
Version: 0.0.1
Summary: RobotFrameworkSlackNotifier1
Home-page: UNKNOWN
Author: Patdroidz
Author-email: patdroidz@gmail.com
License: UNKNOWN
Platform: UNKNOWN
Classifier: Programming Language :: Python :: 3
Classifier: Operating System :: OS Independent
Requires-Python: >=3.6
